DAESIM_preprocess/daesim_forcing.py
DAESIM_preprocess/ozwald_8day.py
DAESIM_preprocess/ozwald_daily.py
DAESIM_preprocess/silo_daily.py
DAESIM_preprocess/slga_soils.py
DAESIM_preprocess/terrain_tiles.py
DAESIM_preprocess/topography.py
daesim_preprocess-0.0.7.dist-info/licenses/LICENSE
daesim_preprocess-0.0.7.dist-info/METADATA
daesim_preprocess-0.0.7.dist-info/WHEEL
daesim_preprocess-0.0.7.dist-info/top_level.txt
daesim_preprocess-0.0.7.dist-info/RECORD
