Metadata-Version: 2.4
Name: DAESIM_preprocess
Version: 0.0.7
Summary: Harvesting environmental forcing data for running the Dynamic Agro-Ecosystem Simulator (DAESIM)
Author-email: Christopher Bradley <christopher.bradley@anu.edu.au>
License-Expression: MIT
Project-URL: Homepage, https://github.com/ChristopherBradley/DAESIM_preprocess
Classifier: Programming Language :: Python :: 3
Classifier: Operating System :: OS Independent
Requires-Python: >=3.9
License-File: LICENSE
Requires-Dist: rioxarray
Requires-Dist: pandas
Requires-Dist: scipy
Requires-Dist: requests
Requires-Dist: pysheds
Requires-Dist: owslib
Requires-Dist: pyproj
Requires-Dist: matplotlib
Requires-Dist: netcdf4
Provides-Extra: dev
Requires-Dist: jupyter; extra == "dev"
Requires-Dist: jupytext; extra == "dev"
Requires-Dist: pytest; extra == "dev"
Requires-Dist: twine; extra == "dev"
Requires-Dist: build; extra == "dev"
Dynamic: license-file
